evalparrot/__init__.py
evalparrot/evaluate_parrot_kilt.py
evalparrot/metric/__init__.py
evalparrot/metric/utils/__init__.py
evalparrot/metric/utils/io.py
evalparrot/metric/utils/multi_run.py
evalparrot/metric/utils/dataset/__init__.py
evalparrot/metric/utils/dataset/kilt_data.py
evalparrot/metric/utils/parrot_utils/__init__.py
evalparrot/metric/utils/parrot_utils/http_utils.py
evalparrot-0.0.6.dist-info/LICENSE
evalparrot-0.0.6.dist-info/METADATA
evalparrot-0.0.6.dist-info/WHEEL
evalparrot-0.0.6.dist-info/top_level.txt
evalparrot-0.0.6.dist-info/RECORD
